{
  "title": "[OffTopic] Looking for 1RK/1BHK for rent near PES EC Campus",
  "content": "If anyone knows of a 1RK/1BHK available for rent near PES EC Campus, please let me know. Would really appreciate any leads",
  "metadata": {
    "id": "1m98mqu",
    "author": "Ok_Government8355",
    "url": "https://www.reddit.com/r/PESU/comments/1m98mqu/offtopic_looking_for_1rk1bhk_for_rent_near_pes_ec/",
    "permalink": "/r/PESU/comments/1m98mqu/offtopic_looking_for_1rk1bhk_for_rent_near_pes_ec/",
    "score": 3,
    "upvote_ratio": 1.0,
    "created_utc": 1753472075.0,
    "flair": "Discussion :snoo_shrug:",
    "nsfw": false
  },
  "comments": [
    "I saw a place yesterday , there is a road (mud road) near Citroen car showroom (approx 800 meters from clg main gate) , there is a good room in that road, don't know about rent and owner"
  ]
}