{
  "title": "orignal documents submission date is postponed, will the session also get posponed?",
  "content": "",
  "metadata": {
    "id": "1e9yv7k",
    "author": "AgreeablePlatypus883",
    "url": "https://www.reddit.com/r/PESU/comments/1e9yv7k/orignal_documents_submission_date_is_postponed/",
    "permalink": "/r/PESU/comments/1e9yv7k/orignal_documents_submission_date_is_postponed/",
    "score": 8,
    "upvote_ratio": 1.0,
    "created_utc": 1721708703.0,
    "flair": "PESSAT/Admission",
    "nsfw": false
  },
  "comments": [
    "Might start on 12th, don’t want it to get too delayed🥲\n└── no way they start on 12th"
  ]
}