{
  "title": "What should my cgpa be to get scholarships which will reduce my fees in btech",
  "content": "",
  "metadata": {
    "id": "1ku0u1q",
    "author": "Brave_University3267",
    "url": "https://www.reddit.com/r/PESU/comments/1ku0u1q/what_should_my_cgpa_be_to_get_scholarships_which/",
    "permalink": "/r/PESU/comments/1ku0u1q/what_should_my_cgpa_be_to_get_scholarships_which/",
    "score": 8,
    "upvote_ratio": 0.83,
    "created_utc": 1748052781.0,
    "flair": "Study Help :table:",
    "nsfw": false
  },
  "comments": [
    "Check the FAQs [https://www.reddit.com/r/PESU/comments/14c1iym/faqs/](https://www.reddit.com/r/PESU/comments/14c1iym/faqs/)\n└── Unable to find it\n    └── ok thats interesting,,, anyway,\n\nso for MRD scholarship which refunds 50% tution fee: you should be in top 5% students AND have cgpa &gt;= 9\n\nfor CNR scholarship which refunds 40% tution fee: you should be in the top 25% students AND have sgpa &gt;= 8.5\n\nand finally a distinction award scholarship which awards 2k if you have sgpa &gt;= 7.75\n\n  \nyou can get only one scholarship in any semester, and you don't get any scholarship in 4th year.\n        └── Man thanks a lott\n            └── Its not enough to just have 8.5 or 9.\nThese are the requirements for each scholarship, but most of the times the cnr(40%) cutoff is around 8.5-8.7 and mrd(50%) is 9.2-9.5 cuz it depends on the top 5% and next 20% and it is not gpa based.\n                └── I see... Thanks bro..\n                    └── Ome more thing to remember is that mrd that's 50% is for the cgpa that's cumulative GPA. The others are semester GPA or sgpa"
  ]
}