{
  "title": "hey, i am asking this behalf of my friend",
  "content": "Is it still possible to upload for counselling through main? i fear it's closed but let me know if I am wrong thanks!",
  "metadata": {
    "id": "1l5frmw",
    "author": "Then_Inevitable8118",
    "url": "https://www.reddit.com/r/PESU/comments/1l5frmw/hey_i_am_asking_this_behalf_of_my_friend/",
    "permalink": "/r/PESU/comments/1l5frmw/hey_i_am_asking_this_behalf_of_my_friend/",
    "score": 5,
    "upvote_ratio": 0.86,
    "created_utc": 1749284064.0,
    "flair": "Admissions",
    "nsfw": false
  },
  "comments": []
}