{
  "id": "1444vvo",
  "title": "which one",
  "content": "[deleted]\n\n[View Poll](https://www.reddit.com/poll/1444vvo)",
  "metadata": {
    "author": "[deleted]",
    "url": "",
    "permalink": "/r/PESU/comments/1444vvo/which_one/",
    "score": 2,
    "created_utc": 1686218095,
    "flair": "Discussion :snoo_shrug:",
    "nsfw": false,
    "type": "submission"
  },
  "comments": [
    {
      "id": "jndnja7",
      "body": "Mit b'lore is a big gamble at this point. No placement statistics, an under-construction campus, and so on. PES  will be a better choice"
    }
  ]
}