{
  "id": "1cleq0d",
  "title": "Matlab",
  "content": "Does anybody know when the matlab exam is for 2nd sem?",
  "metadata": {
    "author": "Original_Bat3183",
    "url": "https://www.reddit.com/r/PESU/comments/1cleq0d/matlab/",
    "permalink": "/r/PESU/comments/1cleq0d/matlab/",
    "score": 2,
    "created_utc": 1714987160,
    "flair": "Discussion :snoo_shrug:",
    "nsfw": false,
    "type": "submission"
  },
  "comments": [
    {
      "id": "l2wylcx",
      "body": "May 15th probably"
    }
  ]
}