{
  "id": "1d0wkzx",
  "title": "Doubt",
  "content": "How to get pes email id?\n",
  "metadata": {
    "author": "United_Earth_TCK1",
    "url": "https://www.reddit.com/r/PESU/comments/1d0wkzx/doubt/",
    "permalink": "/r/PESU/comments/1d0wkzx/doubt/",
    "score": 3,
    "created_utc": 1716710620,
    "flair": "Ask a Senior :redditgold:",
    "nsfw": false,
    "type": "submission"
  },
  "comments": [
    {
      "id": "l5pyze9",
      "body": "U will get it by the end of 2nd sem, if u are a first year rn and haven't till now u should get it soon"
    },
    {
      "id": "l5r1ahi",
      "body": "They will email to you by first sem beginning"
    }
  ]
}