{
  "id": "1d1gmij",
  "title": "Login And Pswd issue",
  "content": "I enrolled the day before yesterday at the rr campus, they gave me a login id and Pswd, but upon trying it, I'm not able to login...what to do?",
  "metadata": {
    "author": "Learner_Bhakt",
    "url": "https://www.reddit.com/r/PESU/comments/1d1gmij/login_and_pswd_issue/",
    "permalink": "/r/PESU/comments/1d1gmij/login_and_pswd_issue/",
    "score": 1,
    "created_utc": 1716774345,
    "flair": "Ask a Senior :redditgold:",
    "nsfw": false,
    "type": "submission"
  },
  "comments": [
    {
      "id": "l5u0h5e",
      "body": "https://www.reddit.com/r/PESU/s/2dul1BIS27"
    },
    {
      "id": "l5u0jqm",
      "body": "Thenku :)"
    },
    {
      "id": "l5u3ufc",
      "body": "You need to reset it the first time you try to use it. \n\nThis was discussed on PESU Discord, so I'd recommend joining that too :)"
    },
    {
      "id": "l5ux056",
      "body": "Thank you sir 😊"
    }
  ]
}