{
  "id": "1ebrv6l",
  "title": "Choose",
  "content": "Guys plz help...\n\n[View Poll](https://www.reddit.com/poll/1ebrv6l)",
  "metadata": {
    "author": "Capable-Back5539",
    "url": "https://www.reddit.com/r/PESU/comments/1ebrv6l/choose/",
    "permalink": "/r/PESU/comments/1ebrv6l/choose/",
    "score": 1,
    "created_utc": 1721904651,
    "flair": "Ask a Senior :redditgold:",
    "nsfw": false,
    "type": "submission"
  },
  "comments": [
    {
      "id": "leutj8a",
      "body": "There is a detailed CS vs CS-AIML comparison in the FAQs: https://bit.ly/pesu-faq\n\nTLDR: CS is a better option because it gives you the flexibility to choose based on your interest and doesn't restrict you to a domain, plus, it's a more recognised branch choice from a higher education point of view. If your goal is only to get a good job however, then CS-AIML placements will be the same as CS placements."
    },
    {
      "id": "levkpsb",
      "body": "why would u chose aiml over core tf, unless ur inclined towards ai"
    },
    {
      "id": "lf0kvei",
      "body": "cause ring road (RR) campus is better than electronic city (EC) campus"
    },
    {
      "id": "lfar85k",
      "body": "other then aesthetics wise, they both are identical. Go for core bro. Ur rsn is dumb. I have talked to seniors who went from ec to rr and they say theres no difference.   \ngo check out FAQs"
    },
    {
      "id": "lfflxr7",
      "body": "ah ok then"
    }
  ]
}