{
  "id": "1eyr1o3",
  "title": "Refund status",
  "content": "I surrended my seat, thou there's no mail or information about when I will get my refund ",
  "metadata": {
    "author": "Lumpy-Breath4671",
    "url": "https://www.reddit.com/r/PESU/comments/1eyr1o3/refund_status/",
    "permalink": "/r/PESU/comments/1eyr1o3/refund_status/",
    "score": 5,
    "created_utc": 1724351978,
    "flair": "PESSAT/Admission",
    "nsfw": false,
    "type": "submission"
  },
  "comments": [
    {
      "id": "ljhso0n",
      "body": "Which branch seat did u surender"
    },
    {
      "id": "ljhy4qk",
      "body": "Cse core"
    },
    {
      "id": "ljlti4j",
      "body": "Which college r u going to now?"
    }
  ]
}