{
  "id": "1f29osh",
  "title": "Transportation to ec campus",
  "content": "I'm living in banglore and abt 40-50mins away from ec campus and would like to know if there is a good transport way to it \nThis is one main requirement for the campus and will determine if I'm taking a seat thru pessat rr campus or kcet ec campus",
  "metadata": {
    "author": "honk888",
    "url": "https://www.reddit.com/r/PESU/comments/1f29osh/transportation_to_ec_campus/",
    "permalink": "/r/PESU/comments/1f29osh/transportation_to_ec_campus/",
    "score": 6,
    "created_utc": 1724737528,
    "flair": "Ask a Senior :redditgold:",
    "nsfw": false,
    "type": "submission"
  },
  "comments": [
    {
      "id": "lk4w1uy",
      "body": "you can take the clg bus if your ok with it or you can easiy take a bmtc bus too"
    },
    {
      "id": "lk4yya9",
      "body": "There's a yellow line metro station opening near the campus next year."
    },
    {
      "id": "lk50bgc",
      "body": "I've heard it will open in December but I live around 10-15 mins away from the nearest station too"
    },
    {
      "id": "lk50ek8",
      "body": "What is it's route, like is it fixed drop points and pickup points or does it change based on students?"
    },
    {
      "id": "lk50fe1",
      "body": "What is it's route, like is it fixed drop points and pickup points or does it change based on students?"
    },
    {
      "id": "lk51gxp",
      "body": "It has a fixed drop off point near people's house from what I hear , as for the fee it's like around 25k or something,  that's what my friend told"
    },
    {
      "id": "lk51vjn",
      "body": "Oh ok thanks for the info"
    },
    {
      "id": "lk538o8",
      "body": "Same question"
    },
    {
      "id": "lk5p2jz",
      "body": "Fixed points, you can check at https://pes.edu/admissions/transportation/"
    },
    {
      "id": "lk5pglh",
      "body": "Is this the same for freshers"
    },
    {
      "id": "lk5phns",
      "body": "Obviously"
    }
  ]
}