{
  "id": "1f3c7fs",
  "title": "Guide me regarding laptop pls !🥲",
  "content": "My budget is 50k (might be less idk) but suggest me a good laptop and is the graphics card required?! I am joining PES RR CSE though ",
  "metadata": {
    "author": "AbbreviationsFar6504",
    "url": "https://www.reddit.com/r/PESU/comments/1f3c7fs/guide_me_regarding_laptop_pls/",
    "permalink": "/r/PESU/comments/1f3c7fs/guide_me_regarding_laptop_pls/",
    "score": 1,
    "created_utc": 1724856725,
    "flair": "Ask a Senior :redditgold:",
    "nsfw": false,
    "type": "submission"
  },
  "comments": [
    {
      "id": "lkcqyxd",
      "body": "If your budget is 50k then go for integrated graphics you wont be able to find a good laptop with dgpu in this segment"
    },
    {
      "id": "lkcsnjj",
      "body": "I've found some laptops with RTX 2050 , should I prefer those *gaming laptops* or take normal ones ?"
    },
    {
      "id": "lkcwg6v",
      "body": "check FAQ"
    },
    {
      "id": "lkcwyhg",
      "body": "Link pls"
    },
    {
      "id": "lkcx633",
      "body": "bruh check the faq in the pinned content in the subreddit"
    },
    {
      "id": "lkcxhb1",
      "body": "Oh sry didn't see, thanks a lot 🥲🙌"
    },
    {
      "id": "lkeb5y4",
      "body": "i would suggest take normal ones cause rtx 2050 is just too outdates and if you go for it prolly you would have to go for a mediocre cpu"
    },
    {
      "id": "lkfne63",
      "body": "Ok thank you 🙌"
    },
    {
      "id": "lkgig3w",
      "body": "No problem"
    }
  ]
}