{
  "id": "1fdafac",
  "title": "Mit manipal cse with Financial technology VS Pes cse with ai main campus.",
  "content": "Help",
  "metadata": {
    "author": "Famous_Hospital_5010",
    "url": "https://www.reddit.com/r/PESU/comments/1fdafac/mit_manipal_cse_with_financial_technology_vs_pes/",
    "permalink": "/r/PESU/comments/1fdafac/mit_manipal_cse_with_financial_technology_vs_pes/",
    "score": 10,
    "created_utc": 1725945733,
    "flair": "PESSAT/Admission",
    "nsfw": false,
    "type": "submission"
  },
  "comments": [
    {
      "id": "lmeboe6",
      "body": "There is no main campus. There is rr campus and ec campus."
    },
    {
      "id": "lmebrv2",
      "body": "Aight sorry man. Rr campus I meant"
    },
    {
      "id": "lmebtfd",
      "body": "Rr campus"
    },
    {
      "id": "lmebvqr",
      "body": "Depends a lot mam I got cse manipal at manipal but my parents didn't allow me saying that the environment is not good, if you're parents say yes then go for and enjoy life"
    },
    {
      "id": "lmef4y4",
      "body": "pes ez"
    },
    {
      "id": "lmefa1m",
      "body": "Why"
    },
    {
      "id": "lmefgtj",
      "body": "better placements, plus ai is better then fin tech, take pes if u dont care about college life too much."
    },
    {
      "id": "lmefsso",
      "body": "Isn't rr campus the main campus?"
    },
    {
      "id": "lmeim5f",
      "body": "Ec waale kehte hai \"there is no main campus\" rr waale kehte hai rr is the main campus, it's pests' way to make themselves feel better."
    },
    {
      "id": "lmej35n",
      "body": "🤣🤣"
    },
    {
      "id": "lmes5jv",
      "body": "Manipal, with this branch specification pes might have a bit of slight edge, but college life would be alot better in MIT. But if you dont care much about college life then pes"
    },
    {
      "id": "lmf41s5",
      "body": "Ikr I along with several of my friends were in the situation lol, but ended up with pes ( same reasons )"
    },
    {
      "id": "lmg22h4",
      "body": "I'd say fintech > AI. Manipal peer group could also be better and friendlier. Both unis have their pros and cons, so pick the field you're interested in."
    },
    {
      "id": "lmm7h13",
      "body": "What environment"
    }
  ]
}