{
  "id": "1fz56tl",
  "title": "Internet portal",
  "content": "whenever i try connecting to the portal it says maximum login failed . whaat on earth am i suppose to do ,if i ask the lab assistance they say its not their problem ",
  "metadata": {
    "author": "Embarrassed-Play-248",
    "url": "https://www.reddit.com/r/PESU/comments/1fz56tl/internet_portal/",
    "permalink": "/r/PESU/comments/1fz56tl/internet_portal/",
    "score": 10,
    "created_utc": 1728407872,
    "flair": "Ask a Senior :redditgold:",
    "nsfw": false,
    "type": "submission"
  },
  "comments": [
    {
      "id": "lqywa9i",
      "body": "Login into your phone and share the hotspot to your laptop .if you are going outside the building don't turn off the wifi , once your back it will automatically connect back"
    },
    {
      "id": "lqywdpi",
      "body": "Hotspot man. The wifi here is unusable most of the time when you need it to work. And fuck the lab assistants most of them are assholes"
    },
    {
      "id": "lqyy9ks",
      "body": "Email them"
    },
    {
      "id": "lr0zn5x",
      "body": "It doesn't just connect anywhere "
    },
    {
      "id": "lr0zocp",
      "body": "Can u give the mail id"
    },
    {
      "id": "lr1msil",
      "body": "ITTeam.rr@pes.edu"
    },
    {
      "id": "lr2iv0t",
      "body": "for ec campus?"
    },
    {
      "id": "lr2m8fm",
      "body": "I'm not sure sorry"
    },
    {
      "id": "lr352u3",
      "body": "itteam.ec@pes.edu"
    }
  ]
}