{
  "id": "1juyhoh",
  "title": "At was damn fun but",
  "content": "Fk u guys💓",
  "metadata": {
    "author": "DhruvaSync",
    "url": "https://i.redd.it/7hx3l4ebxqte1.jpeg",
    "permalink": "/r/PESU/comments/1juyhoh/at_was_damn_fun_but/",
    "score": 68,
    "created_utc": 1744176978,
    "flair": "Rant :snoo_facepalm:",
    "nsfw": false,
    "type": "submission"
  },
  "comments": [
    {
      "id": "mm62jc3",
      "body": "which artists performed in the fest?"
    },
    {
      "id": "mm62tgy",
      "body": "Mohit chauhan and kullu(aditya kulshresht)"
    }
  ]
}