{
  "id": "1kmawh8",
  "title": "PES CSE RR campus vs VIT Vellore CSE CAT 3",
  "content": "I will mostly get PES CSE through JEE mains and I've been allotted CSE in CAT 3 for VIT and I was wondering which college is better based on placements and college life. ",
  "metadata": {
    "author": "Brilliant_Hall7913",
    "url": "https://www.reddit.com/r/PESU/comments/1kmawh8/pes_cse_rr_campus_vs_vit_vellore_cse_cat_3/",
    "permalink": "/r/PESU/comments/1kmawh8/pes_cse_rr_campus_vs_vit_vellore_cse_cat_3/",
    "score": 5,
    "created_utc": 1747214956,
    "flair": "Ask a Senior :redditgold:",
    "nsfw": false,
    "type": "submission"
  },
  "comments": [
    {
      "id": "ms8qbq7",
      "body": "Definitely PES....no other thoughts...."
    },
    {
      "id": "ms8vvmm",
      "body": "PES for placements any day."
    },
    {
      "id": "ms962zr",
      "body": "how much did you get in jee mains"
    },
    {
      "id": "mt9kthx",
      "body": "Is pes really good plz do tell ..???"
    }
  ]
}