{
  "id": "1kv9ead",
  "title": "Guys going for offline councelling who aren't from karnataka!! Please DM",
  "content": "Same as title.  \nI was thinking of making a group of upcoming freshers for people with this situation , if you are down then please dm or just comment.",
  "metadata": {
    "author": "JobWorking",
    "url": "https://www.reddit.com/r/PESU/comments/1kv9ead/guys_going_for_offline_councelling_who_arent_from/",
    "permalink": "/r/PESU/comments/1kv9ead/guys_going_for_offline_councelling_who_arent_from/",
    "score": 3,
    "created_utc": 1748197500,
    "flair": "Discussion :snoo_shrug:",
    "nsfw": false,
    "type": "submission"
  },
  "comments": [
    {
      "id": "mu7posr",
      "body": "you could just join the discord server?"
    },
    {
      "id": "mu7qf1u",
      "body": "nah re ig aise particular situation mai whatsapp better hoga"
    }
  ]
}