{
  "id": "1l5j12v",
  "title": "5th Sem Electives for Computer Science",
  "content": "I am totally confused about what to choose for Electives 1 and 2. I just want to select subjects that are scoring. Can you suggest which subjects are good for scoring marks? I want to increase my CGPA.",
  "metadata": {
    "author": "Safe_Presentation741",
    "url": "https://www.reddit.com/r/PESU/comments/1l5j12v/5th_sem_electives_for_computer_science/",
    "permalink": "/r/PESU/comments/1l5j12v/5th_sem_electives_for_computer_science/",
    "score": 1,
    "created_utc": 1749297153,
    "flair": "Ask a Senior :redditgold:",
    "nsfw": false,
    "type": "submission"
  },
  "comments": [
    {
      "id": "mwh5xb7",
      "body": "Ac for first elective is probably one of the easiest.not too sure for second \n\nAnd if you're aiml, take whichever elective a guy called doreswamy takes. The average isa marks are like 38/40"
    },
    {
      "id": "mwh6b48",
      "body": "i am from cse which one is the marks scoring i want to take that pls tell me"
    },
    {
      "id": "mwh6pyy",
      "body": "I just told you are you dislexyc"
    }
  ]
}