{
  "id": "1l782wu",
  "title": "PES CS Core (EC Campus) vs VIT Vellore CS with Cybersecurity – Need Help Deciding",
  "content": "",
  "metadata": {
    "author": "Emergency-Eagle5479",
    "url": "https://www.reddit.com/r/PESU/comments/1l782wu/pes_cs_core_ec_campus_vs_vit_vellore_cs_with/",
    "permalink": "/r/PESU/comments/1l782wu/pes_cs_core_ec_campus_vs_vit_vellore_cs_with/",
    "score": 3,
    "created_utc": 1749483659,
    "flair": "Admissions",
    "nsfw": false,
    "type": "submission"
  },
  "comments": [
    {
      "id": "mwunk6u",
      "body": "Core is always better , plus vellore the rat race will be insane , i think so you should stick around"
    },
    {
      "id": "mwv8py0",
      "body": "vit"
    },
    {
      "id": "mwvc56s",
      "body": "Post/comment contains advice or information that is incorrect, misleading, unethical, or potentially harmful. Please fact-check before posting and refer to reliable sources when giving guidance."
    },
    {
      "id": "mwxbkqf",
      "body": "Stick with PES, i chose pes over VIT Vellore CSE, Vit will be a pure rat race and less exposure....come here to PES, I bet you won't regret it...."
    },
    {
      "id": "mwy9jvb",
      "body": "ty"
    },
    {
      "id": "mwy9mge",
      "body": "ty...ec campus wont make a diff?"
    },
    {
      "id": "mwz3gyq",
      "body": "Slight difference, otherwise its good"
    },
    {
      "id": "mwz5ybg",
      "body": "No difference, placements are combined ,but yeah rr is more lively i headd"
    }
  ]
}