{
  "id": "1ng70se",
  "title": "[Announcement] Ticket exchange for garba night",
  "content": "So I bought a ticket for the 2nd day of garba night which is 28, but due to some work I won't be here on 28, is there anyone who would want to exchange their ticket of 27th with mine?",
  "metadata": {
    "author": "Big-Swimmer7083",
    "url": "https://www.reddit.com/r/PESU/comments/1ng70se/announcement_ticket_exchange_for_garba_night/",
    "permalink": "/r/PESU/comments/1ng70se/announcement_ticket_exchange_for_garba_night/",
    "score": 3,
    "created_utc": 1757793117,
    "flair": "ANNOUNCEMENT :snoo:",
    "nsfw": false,
    "type": "submission"
  },
  "comments": [
    {
      "id": "ne42t11",
      "body": "You cant exchange this"
    },
    {
      "id": "ne4e6hs",
      "body": "they're not gonna double check with your srn tho"
    }
  ]
}