{
  "id": "17fz24p",
  "title": "Help pesticides",
  "content": "What the name of literary smort pes club rr campus?",
  "metadata": {
    "root_comment_id": "k6dn8s3",
    "post_id": "17fz24p",
    "author": "Sea_Mail_2026",
    "url": "https://www.reddit.com/r/PESU/comments/17fz24p/help_pesticides/",
    "permalink": "https://reddit.com/r/PESU/comments/17fz24p/help_pesticides/",
    "score": 7,
    "upvote_ratio": 0.8999999761581421,
    "created_utc": 1698217953,
    "flair": "Ask a Senior :redditgold:",
    "nsfw": false
  },
  "comments": [
    {
      "id": "k6dn8s3",
      "body": "I think you are referring to this club: https://www.instagram.com/writeangle.pesu/"
    },
    {
      "id": "k6f6ixj",
      "body": "The writing club is Write Angle as mentioned in the other comment,  but the book exchange event was from a club named Linguista. I can get you in touch with the club head if you want."
    },
    {
      "id": "k6k4x03",
      "body": "Its Linguista!!!\n\nhere is the link to their ig: https://www.instagram.com/linguista.club/"
    }
  ]
}