{
  "id": "1by4esh",
  "title": "Would withdrawing a course be a better option?",
  "content": "This is an entirely hypothetical situation - let's assume I did really bad in both my isas and my final isa score is 10/50. \n\nIn such a scenario is it better to just withdraw the course and write the backlog?\nLet's assume I score 90 in esa in this case that would give me a grade of D (assuming no grace marks). \n\nSurely scoring 90 in backlog would give me a better grade when isa score isn't considered.\n",
  "metadata": {
    "root_comment_id": "kygvyo1",
    "post_id": "1by4esh",
    "author": "Accomplished_Arm_835",
    "url": "https://www.reddit.com/r/PESU/comments/1by4esh/would_withdrawing_a_course_be_a_better_option/",
    "permalink": "https://reddit.com/r/PESU/comments/1by4esh/would_withdrawing_a_course_be_a_better_option/",
    "score": 4,
    "upvote_ratio": 0.8399999737739563,
    "created_utc": 1712496216,
    "flair": "Discussion :snoo_shrug:",
    "nsfw": false
  },
  "comments": [
    {
      "id": "kygvyo1",
      "body": "Yeah that's correct. At least I think it is"
    },
    {
      "id": "kyh48aa",
      "body": "Yes it is, but the question is will you be able to do it? Cuz you will be having 1 extra subject to study along with 5 main subjects. You should better reconsider the decision.\n└── Ah ok. Wasn't asking for me, this just came to my mind so i thought I'd ask here"
    }
  ]
}