{
  "id": "1c6pzt2",
  "title": "How are your placements for MBA!?",
  "content": "This is extremely important for me. Without mentioning your name, please tell me how your placements have been going, which specialization is getting many placements and your package. I have joined PES for MBA and am now getting scared😨😨 that too management quota",
  "metadata": {
    "root_comment_id": "l06jzed",
    "post_id": "1c6pzt2",
    "author": "East-Understanding61",
    "url": "https://www.reddit.com/r/PESU/comments/1c6pzt2/how_are_your_placements_for_mba/",
    "permalink": "https://reddit.com/r/PESU/comments/1c6pzt2/how_are_your_placements_for_mba/",
    "score": 2,
    "upvote_ratio": 0.75,
    "created_utc": 1713400365,
    "flair": "Ask a Senior :redditgold:",
    "nsfw": false
  },
  "comments": [
    {
      "id": "l06jzed",
      "body": "How much was the fees asking out of curiosity\n└── It was 14lac for 2 years\n    └── 14 lac? In another thread people were saying rvim 1.3 lac for one year and only 50k difference in PES.\n        └── That would be for admission through pgcet\nThrough the management quota it's 14lac!\n            └── God that's a lot."
    },
    {
      "id": "liuv8xx",
      "body": "Would appreciate it if someone can share their placement info"
    }
  ]
}