{
  "id": "1czih17",
  "title": "How is bca?",
  "content": "Hey guys how is the placement stats for bca.\nHow is the fee structure and is pessat the only way to get in bca\n\nPs. If someone has a excel containing the stats for placements ..please share",
  "metadata": {
    "root_comment_id": "l5gyr8n",
    "post_id": "1czih17",
    "author": "rithu13",
    "url": "https://www.reddit.com/r/PESU/comments/1czih17/how_is_bca/",
    "permalink": "https://reddit.com/r/PESU/comments/1czih17/how_is_bca/",
    "score": 3,
    "upvote_ratio": 1,
    "created_utc": 1716550018,
    "flair": "Ask a Senior :redditgold:",
    "nsfw": false
  },
  "comments": [
    {
      "id": "l5gyr8n",
      "body": "there's no placement stats because they restarted the program just last year, professors will encourage you to do mca at pes after completing bca but there's opportunities for you to connect w alumni and you can always look for jobs through connections. we were told that if we truly are interested in placements then they'll help us out.\n\nmy batch has to pay 2L per year, and pessat for us was just an interview round, not sure how it is this year."
    }
  ]
}