{
  "id": "1f8n1ap",
  "title": "PESU median beats RVCE ( 2024 ) !?",
  "content": "https://preview.redd.it/enh2vx0fsqmd1.png?width=1749&format=png&auto=webp&s=285d5cbdc320d333186890cdbe2bbac645a11ce2\n\ndamn.",
  "metadata": {
    "root_comment_id": "llfkkw7",
    "post_id": "1f8n1ap",
    "author": "PrestigiousLow9589",
    "url": "https://www.reddit.com/r/PESU/comments/1f8n1ap/pesu_median_beats_rvce_2024/",
    "permalink": "https://reddit.com/r/PESU/comments/1f8n1ap/pesu_median_beats_rvce_2024/",
    "score": 39,
    "upvote_ratio": 0.8999999761581421,
    "created_utc": 1725433765,
    "flair": "ANNOUNCEMENT :snoo:",
    "nsfw": false
  },
  "comments": [
    {
      "id": "llfkkw7",
      "body": "Seeing only 1582 eligible students in PES, I thought these stats are only CSE + CSE AI/ML. Correct me if I am wrong here.\n└── AIML batch hasn't sit for placements yet\n    └── ok"
    },
    {
      "id": "llfl8z5",
      "body": "Does this data also include Aiml at pes also?"
    },
    {
      "id": "llfllcb",
      "body": "PESU Median is only for CSE in rr and ec\nWhereas RVCE its across even branches like mechanical, chemical, biotech,iem etc\nWouldnt even be close if ece eee biotech mech of pesu be included\n└── It's an overall median , not just CSE. , 1584 eligible students isnt even the total of RR+EC CSE , not to mention that not all students are eligible"
    },
    {
      "id": "llfnbfu",
      "body": "1500 students is not even 50% of the total students in both campuses... That's horrible placements percentage\n└── Placement's arent over yet. It's just the data till now\n    └── Pes university in general doens't have a good placement percentage, their biggest flaw is the gigantic intake they have\n        └── Bro is from RVU but is commenting like he's from IIT-B😂😂💀💀\n            └── 🤣🤣🤣🤣🤣"
    },
    {
      "id": "llhbi8g",
      "body": "6 branches vs 14 branches\n\nRV has better placement percentage aswell\n└── It's 55% for both last year ig\n    └── Rvce was around 72%\n        └── Cs was 75%\n            └── 1122 offers in 2023 no way the placement is. 56% overall\n\nWhats your source?\n                └──  Can I dm?\n                    └── Sure"
    },
    {
      "id": "lliav6r",
      "body": "Pes has massive intake how do they manage placement for so many students\n└── jawahar's janitors"
    }
  ]
}