{
  "id": "1gnvyy2",
  "title": "Shoutout to Maaya 2024",
  "content": "Just wanted to take a moment to appreciate all the hard work the organizers did at Maaya this year.   \nNemophillis and DJ rhea were mad entertaining. The stalls were good (ngl, would have been nice if they were a bit cheaper tho) . The activities were sick as well.   \nThanks to everyone who made Maaya possible. ",
  "metadata": {
    "root_comment_id": "lwdwdq4",
    "post_id": "1gnvyy2",
    "author": "Subject_Ingenuity375",
    "url": "https://www.reddit.com/r/PESU/comments/1gnvyy2/shoutout_to_maaya_2024/",
    "permalink": "https://reddit.com/r/PESU/comments/1gnvyy2/shoutout_to_maaya_2024/",
    "score": 34,
    "upvote_ratio": 0.7900000214576721,
    "created_utc": 1731226495,
    "flair": "Pride Of PESU",
    "nsfw": false
  },
  "comments": [
    {
      "id": "lwdwdq4",
      "body": "Saturday was lit af 🔥🔥"
    },
    {
      "id": "lwe161k",
      "body": "Dj rhea saved the day ngl\n└── Nemophillis was better imo"
    },
    {
      "id": "lwj6l33",
      "body": "Damn, good to hear this. It was so crappy while I was there.."
    },
    {
      "id": "lwr6817",
      "body": "as a massive hater of pes, i agree"
    },
    {
      "id": "lx0mlwp",
      "body": "The stalls being higher priced is because the event charges those brands rent amount for setting up the table and everything there as well. That's why the food brands have to charge higher than their actual mrp for those same products. But the difference is quite nominal I believe.\n└── yeah it is understandable, just said it would have been nice if they were cheaper.\n    └── Fairs"
    }
  ]
}