{
  "id": "1hncq1w",
  "title": "Did you guys get this notification ",
  "content": "",
  "metadata": {
    "root_comment_id": "m40msuz",
    "post_id": "1hncq1w",
    "author": "Still-Elderberry-658",
    "url": "https://i.redd.it/aobfq8ujjd9e1.png",
    "permalink": "https://reddit.com/r/PESU/comments/1hncq1w/did_you_guys_get_this_notification/",
    "score": 1,
    "upvote_ratio": 1,
    "created_utc": 1735297889,
    "flair": "ANNOUNCEMENT :snoo:",
    "nsfw": false
  },
  "comments": [
    {
      "id": "m40msuz",
      "body": "Is this fr ?"
    }
  ]
}