{
  "id": "1i4qro3",
  "title": "PES admission through JEE percentile",
  "content": "Hey, If I want to get admission to pes through JEE percentile... What is the minimum percentile I should maintain for Computer Science?",
  "metadata": {
    "root_comment_id": "m7xm43t",
    "post_id": "1i4qro3",
    "author": "gskneeraj",
    "url": "https://www.reddit.com/r/PESU/comments/1i4qro3/pes_admission_through_jee_percentile/",
    "permalink": "https://reddit.com/r/PESU/comments/1i4qro3/pes_admission_through_jee_percentile/",
    "score": 5,
    "upvote_ratio": 0.8600000143051147,
    "created_utc": 1737262487,
    "flair": "Ask a Senior :redditgold:",
    "nsfw": false
  },
  "comments": [
    {
      "id": "m7xm43t",
      "body": "96-97 to be safe"
    },
    {
      "id": "m7xrgo8",
      "body": "Prolly like 94"
    },
    {
      "id": "m7xux2t",
      "body": "97%ile most likely be higher to be safe."
    },
    {
      "id": "m7yfng5",
      "body": "Don’t :)\n└── The college lacks the culture for CP\n    └── CP as in compi programming? how so?"
    },
    {
      "id": "m7ylwdb",
      "body": "since only like10% of the seats were thru jee the cutoff was high around98 ig so now that 60%(?) of the seats are now thru jee its gonna be like 95-97 ish"
    }
  ]
}