{
  "id": "1i52qge",
  "title": "Guys should I do my BBA at PESU RR or JAIN CMS?",
  "content": "I’ve gotten provisional admissions offers from both and want to know which is better? In terms of faculty, placements, hostel and all?",
  "metadata": {
    "root_comment_id": "m8nyrkv",
    "post_id": "1i52qge",
    "author": "aparnaaas",
    "url": "https://www.reddit.com/r/PESU/comments/1i52qge/guys_should_i_do_my_bba_at_pesu_rr_or_jain_cms/",
    "permalink": "https://reddit.com/r/PESU/comments/1i52qge/guys_should_i_do_my_bba_at_pesu_rr_or_jain_cms/",
    "score": 7,
    "upvote_ratio": 1,
    "created_utc": 1737305155,
    "flair": "PESSAT/Admission",
    "nsfw": false
  },
  "comments": [
    {
      "id": "m8nyrkv",
      "body": "From my research, PESU RR. Got terrible reviews about Jain\n└── what are the reviews of jain? so far seen only good ones"
    }
  ]
}