{
  "id": "1iymhih",
  "title": "Flats near PES",
  "content": "Does anyone know good flats or a decent pg for girls around the college?Also is anyone moving out of Vasundhara Kritika next semester?",
  "metadata": {
    "root_comment_id": "mex2smt",
    "post_id": "1iymhih",
    "author": "Historical-Rip8847",
    "url": "https://www.reddit.com/r/PESU/comments/1iymhih/flats_near_pes/",
    "permalink": "https://reddit.com/r/PESU/comments/1iymhih/flats_near_pes/",
    "score": 4,
    "upvote_ratio": 0.8399999737739563,
    "created_utc": 1740573243,
    "flair": "Discussion :snoo_shrug:",
    "nsfw": false
  },
  "comments": [
    {
      "id": "mex2smt",
      "body": "If you're looking for information on vacating tenants at Vasundhara, you'll have to contact the owners and/or the broker (there was a single broker in charge a few years ago if I remember). Walk up to the building and ask for contact details from the security"
    }
  ]
}