{
  "id": "1k50qb7",
  "title": "Internship prep help 🙏",
  "content": "Seniors , any suggestions on how to get good internships in second year or third year , I’m in first year right now , is there anything I should start doing now ? Like learning something or extra courses etc…\n\nReplys would be of great help , thanks",
  "metadata": {
    "root_comment_id": "mohlbks",
    "post_id": "1k50qb7",
    "author": "bitwise_sage",
    "url": "https://www.reddit.com/r/PESU/comments/1k50qb7/internship_prep_help/",
    "permalink": "https://reddit.com/r/PESU/comments/1k50qb7/internship_prep_help/",
    "score": 11,
    "upvote_ratio": 0.8700000047683716,
    "created_utc": 1745307968,
    "flair": "Ask a Senior :redditgold:",
    "nsfw": false
  },
  "comments": [
    {
      "id": "mohlbks",
      "body": "Leetcode/DSA\nBut right now just focus on your interests and build quality projects"
    }
  ]
}