{
  "id": "1l6zfwo",
  "title": "Guys a small doubt regarding hostels",
  "content": "Guys can bangalore students through pesu counselling have hostel access?",
  "metadata": {
    "root_comment_id": "mwss9rv",
    "post_id": "1l6zfwo",
    "author": "MaintenanceSelect739",
    "url": "https://www.reddit.com/r/PESU/comments/1l6zfwo/guys_a_small_doubt_regarding_hostels/",
    "permalink": "https://reddit.com/r/PESU/comments/1l6zfwo/guys_a_small_doubt_regarding_hostels/",
    "score": 6,
    "upvote_ratio": 0.8799999952316284,
    "created_utc": 1749457571,
    "flair": "Discussion :snoo_shrug:",
    "nsfw": false
  },
  "comments": [
    {
      "id": "mwss9rv",
      "body": "cfbr"
    },
    {
      "id": "mwsstf7",
      "body": "Someone in previous post said that the banglore students can apply after the non karnataka students\n└── Also does anyone have the classroom pictures of ec campus computer science classes"
    }
  ]
}