{
  "id": "1m9xafa",
  "title": "[Question] is there a freshers party for both the campus?",
  "content": "",
  "metadata": {
    "root_comment_id": "n5aaiey",
    "post_id": "1m9xafa",
    "author": "Capital-Armadillo793",
    "url": "https://www.reddit.com/r/PESU/comments/1m9xafa/question_is_there_a_freshers_party_for_both_the/",
    "permalink": "https://reddit.com/r/PESU/comments/1m9xafa/question_is_there_a_freshers_party_for_both_the/",
    "score": 1,
    "upvote_ratio": 1,
    "created_utc": 1753546447,
    "flair": "Discussion :snoo_shrug:",
    "nsfw": false
  },
  "comments": [
    {
      "id": "n5aaiey",
      "body": "Hi u/Capital-Armadillo793, your post was removed because it appears to be empty.\n\nIf you're asking a question or starting a discussion, please make sure to include text in the body of your post. An empty post doesn’t help others understand what you need, and it can’t lead to a productive discussion.\n\n\n*I am a bot, and this action was performed automatically. Please [contact the moderators of this subreddit](/message/compose/?to=/r/PESU) if you have any questions or concerns.*"
    }
  ]
}