{
  "id": "1nmqlhh",
  "title": "[Placements] Which companies qualify as Dream Tier?",
  "content": "How can I find out which companies I’m eligible to apply to after receiving a Tier 1? If the difference in pay is substantial, am I still allowed to apply?",
  "metadata": {
    "root_comment_id": "nfeo5x7",
    "post_id": "1nmqlhh",
    "author": "AloneRice6234",
    "url": "https://www.reddit.com/r/PESU/comments/1nmqlhh/placements_which_companies_qualify_as_dream_tier/",
    "permalink": "https://reddit.com/r/PESU/comments/1nmqlhh/placements_which_companies_qualify_as_dream_tier/",
    "score": 11,
    "upvote_ratio": 1,
    "created_utc": 1758457515,
    "flair": "Placements 🤑",
    "nsfw": false
  },
  "comments": [
    {
      "id": "nfeprdq",
      "body": "1. It will explicitly state so in the placement emails.\n2. No. Does not matter if the difference is substantial or not.\n├── This there has been no mention of dream tier for any company actually\n│   └── That means none of the companies so far have been deemed to be dream companies by the placement cell. It's PES who decides if they are eligible to be in that tier.\n│       ├── Could you please let me know what the placement cell considers as the ‘dream tier’ cutoff?\n│       │   └── It differs from batch to batch and depends on the CTC offered. I think it was >50L the last time I read about it.\n│       └── Apple is dream tier, but it wasn’t mentioned anywhere in any mail. So, many people who got placed thought they couldn’t even sit for Apple, but apparently, they could.\n└── Is Confluent considered/was considered dream tier in the past? They are offering 33 Lakhs as base (not CTC)\n    └── No, it wasn't considered."
    },
    {
      "id": "nfes1zv",
      "body": "Apple only"
    }
  ]
}